<?xml version="1.0" encoding="UTF-8"?>
<Export generator="Cache" version="25">
<Class name="Dance.Utils.Init.Country">
<Super>Stc.Utils.Init.BaseInit</Super>
<TimeCreated>63296,4328.569075</TimeCreated>

<Parameter name="PClassName">
<Default>Country</Default>
</Parameter>

<Method name="Import">
<ClassMethod>1</ClassMethod>
<ReturnType>%Status</ReturnType>
<Implementation><![CDATA[
	do ##class(Dance.Data.Country).%KillExtent()
	
	set count = 0
	set countriesEng($I(count)) =  "Afghanistan"
	set countriesEng($I(count)) =  "Albania"
	set countriesEng($I(count)) =  "Algeria"
	set countriesEng($I(count)) =  "American Samoa"
	set countriesEng($I(count)) =  "Andorra"
	set countriesEng($I(count)) =  "Angola"
	set countriesEng($I(count)) =  "Anguilla"
	set countriesEng($I(count)) =  "Antarctica"
	set countriesEng($I(count)) =  "Antigua and Barbuda"
	set countriesEng($I(count)) =  "Argentina"
	set countriesEng($I(count)) =  "Armenia"
	set countriesEng($I(count)) =  "Aruba"
	set countriesEng($I(count)) =  "Australia"
	set countriesEng($I(count)) =  "Austria"
	set countriesEng($I(count)) =  "Azerbaijan"
	set countriesEng($I(count)) =  "Bahamas"
	set countriesEng($I(count)) =  "Bahrain"
	set countriesEng($I(count)) =  "Bangladesh"
	set countriesEng($I(count)) =  "Barbados"
	set countriesEng($I(count)) =  "Belarus"
	set countriesEng($I(count)) =  "Belgium"
	set countriesEng($I(count)) =  "Belize"
	set countriesEng($I(count)) =  "Benin"
	set countriesEng($I(count)) =  "Bermuda"
	set countriesEng($I(count)) =  "Bhutan"
	set countriesEng($I(count)) =  "Bolivia"
	set countriesEng($I(count)) =  "Bosnia and Herzegovina"
	set countriesEng($I(count)) =  "Botswana"
	set countriesEng($I(count)) =  "Bouvet Island"
	set countriesEng($I(count)) =  "Brazil"
	set countriesEng($I(count)) =  "Brunei Darussalam"
	set countriesEng($I(count)) =  "Bulgaria"
	set countriesEng($I(count)) =  "Burkina Faso"
	set countriesEng($I(count)) =  "Burundi"
	set countriesEng($I(count)) =  "Cambodia"
	set countriesEng($I(count)) =  "Cameroon"
	set countriesEng($I(count)) =  "Canada"
	set countriesEng($I(count)) =  "Cape Verde"
	set countriesEng($I(count)) =  "Cayman Islands"
	set countriesEng($I(count)) =  "Central African Republic"
	set countriesEng($I(count)) =  "Chad"
	set countriesEng($I(count)) =  "Chile"
	set countriesEng($I(count)) =  "China, People's Republic of"
	set countriesEng($I(count)) =  "Chinese Taipei"
	set countriesEng($I(count)) =  "Christmas Island"
	set countriesEng($I(count)) =  "Cocos (Keeling) Islands"
	set countriesEng($I(count)) =  "Colombia"
	set countriesEng($I(count)) =  "Comoros"
	set countriesEng($I(count)) =  "Congo, Republic of the"
	set countriesEng($I(count)) =  "Cook Islands"
	set countriesEng($I(count)) =  "Costa Rica"
	set countriesEng($I(count)) =  "Côte d'Ivoire"
	set countriesEng($I(count)) =  "Croatia"
	set countriesEng($I(count)) =  "Cuba"
	set countriesEng($I(count)) =  "Cyprus"
	set countriesEng($I(count)) =  "Czech Republic"
	set countriesEng($I(count)) =  "Denmark"
	set countriesEng($I(count)) =  "Djibouti"
	set countriesEng($I(count)) =  "Dominica"
	set countriesEng($I(count)) =  "Dominican Republic"
	set countriesEng($I(count)) =  "Ecuador"
	set countriesEng($I(count)) =  "EGYPT"
	set countriesEng($I(count)) =  "El Salvador"
	set countriesEng($I(count)) =  "England"
	set countriesEng($I(count)) =  "Equatorial Guinea"
	set countriesEng($I(count)) =  "Estonia"
	set countriesEng($I(count)) =  "Ethiopia"
	set countriesEng($I(count)) =  "Falkland Islands"
	set countriesEng($I(count)) =  "Faroe Islands"
	set countriesEng($I(count)) =  "Fiji"
	set countriesEng($I(count)) =  "Finland"
	set countriesEng($I(count)) =  "France"
	set countriesEng($I(count)) =  "French Guiana"
	set countriesEng($I(count)) =  "French Polynesia"
	set countriesEng($I(count)) =  "Gabon"
	set countriesEng($I(count)) =  "Gambia"
	set countriesEng($I(count)) =  "Georgia"
	set countriesEng($I(count)) =  "Germany"
	set countriesEng($I(count)) =  "Ghana"
	set countriesEng($I(count)) =  "Gibraltar"
	set countriesEng($I(count)) =  "Greece"
	set countriesEng($I(count)) =  "Greenland"
	set countriesEng($I(count)) =  "Grenada"
	set countriesEng($I(count)) =  "Guadeloupe"
	set countriesEng($I(count)) =  "Guam"
	set countriesEng($I(count)) =  "Guatemala"
	set countriesEng($I(count)) =  "Guinea"
	set countriesEng($I(count)) =  "Guinea-Bissau"
	set countriesEng($I(count)) =  "Guyana"
	set countriesEng($I(count)) =  "Haiti"
	set countriesEng($I(count)) =  "Heard Island and McDonald Islands"
	set countriesEng($I(count)) =  "Honduras"
	set countriesEng($I(count)) =  "Hong Kong"
	set countriesEng($I(count)) =  "Hungary"
	set countriesEng($I(count)) =  "Iceland"
	set countriesEng($I(count)) =  "India"
	set countriesEng($I(count)) =  "Indonesia"
	set countriesEng($I(count)) =  "Iran, Islamic Republic of"
	set countriesEng($I(count)) =  "Iraq"
	set countriesEng($I(count)) =  "Ireland, Republic of"
	set countriesEng($I(count)) =  "Israel"
	set countriesEng($I(count)) =  "Italy"
	set countriesEng($I(count)) =  "Jamaica"
	set countriesEng($I(count)) =  "Japan"
	set countriesEng($I(count)) =  "Jordan"
	set countriesEng($I(count)) =  "Kazakhstan"
	set countriesEng($I(count)) =  "Kenya"
	set countriesEng($I(count)) =  "Kiribati"
	set countriesEng($I(count)) =  "Korea"
	set countriesEng($I(count)) =  "Korea, Democratic People's Republic of"
	set countriesEng($I(count)) =  "Kuwait"
	set countriesEng($I(count)) =  "Kyrgyzstan"
	set countriesEng($I(count)) =  "Lao People's Democratic Republic"
	set countriesEng($I(count)) =  "Latvia"
	set countriesEng($I(count)) =  "Lebanon"
	set countriesEng($I(count)) =  "Lesotho"
	set countriesEng($I(count)) =  "Liberia"
	set countriesEng($I(count)) =  "Libyan Arab Jamahiriya"
	set countriesEng($I(count)) =  "Liechtenstein"
	set countriesEng($I(count)) =  "Lithuania"
	set countriesEng($I(count)) =  "Luxembourg"
	set countriesEng($I(count)) =  "Macau"
	set countriesEng($I(count)) =  "Macedonia"
	set countriesEng($I(count)) =  "Madagascar"
	set countriesEng($I(count)) =  "Malawi"
	set countriesEng($I(count)) =  "Malaysia"
	set countriesEng($I(count)) =  "Maldives"
	set countriesEng($I(count)) =  "Mali"
	set countriesEng($I(count)) =  "Malta"
	set countriesEng($I(count)) =  "Marshall Islands"
	set countriesEng($I(count)) =  "Martinique"
	set countriesEng($I(count)) =  "Mauritania"
	set countriesEng($I(count)) =  "Mauritius"
	set countriesEng($I(count)) =  "Mayotte"
	set countriesEng($I(count)) =  "Mexico"
	set countriesEng($I(count)) =  "Micronesia, Federated States of"
	set countriesEng($I(count)) =  "Moldova"
	set countriesEng($I(count)) =  "Monaco"
	set countriesEng($I(count)) =  "Mongolia"
	set countriesEng($I(count)) =  "Montenegro"
	set countriesEng($I(count)) =  "Montserrat"
	set countriesEng($I(count)) =  "Morocco"
	set countriesEng($I(count)) =  "Mozambique"
	set countriesEng($I(count)) =  "Myanmar"
	set countriesEng($I(count)) =  "Namibia"
	set countriesEng($I(count)) =  "Nauru"
	set countriesEng($I(count)) =  "Nepal"
	set countriesEng($I(count)) =  "Netherlands"
	set countriesEng($I(count)) =  "Netherlands Antilles"
	set countriesEng($I(count)) =  "New Caledonia"
	set countriesEng($I(count)) =  "New Zealand"
	set countriesEng($I(count)) =  "Nicaragua"
	set countriesEng($I(count)) =  "Niger"
	set countriesEng($I(count)) =  "Nigeria"
	set countriesEng($I(count)) =  "Niue"
	set countriesEng($I(count)) =  "Norfolk Island"
	set countriesEng($I(count)) =  "Northern Ireland"
	set countriesEng($I(count)) =  "Northern Mariana Islands"
	set countriesEng($I(count)) =  "Norway"
	set countriesEng($I(count)) =  "Oman"
	set countriesEng($I(count)) =  "Pakistan"
	set countriesEng($I(count)) =  "Palau"
	set countriesEng($I(count)) =  "Panama"
	set countriesEng($I(count)) =  "Papua New Guinea"
	set countriesEng($I(count)) =  "Paraguay"
	set countriesEng($I(count)) =  "Peru"
	set countriesEng($I(count)) =  "Philippines"
	set countriesEng($I(count)) =  "Pitcairn"
	set countriesEng($I(count)) =  "Poland"
	set countriesEng($I(count)) =  "Portugal"
	set countriesEng($I(count)) =  "Puerto Rico"
	set countriesEng($I(count)) =  "Qatar"
	set countriesEng($I(count)) =  "Republic of Kosovo"
	set countriesEng($I(count)) =  "Réunion"
	set countriesEng($I(count)) =  "Romania"
	set countriesEng($I(count)) =  "Russian Federation"
	set countriesEng($I(count)) =  "Rwanda"
	set countriesEng($I(count)) =  "Saint Helena"
	set countriesEng($I(count)) =  "Saint Kitts and Nevis"
	set countriesEng($I(count)) =  "Saint Lucia"
	set countriesEng($I(count)) =  "Saint Pierre and Miquelon"
	set countriesEng($I(count)) =  "Saint Vincent and the Grenadines"
	set countriesEng($I(count)) =  "Samoa"
	set countriesEng($I(count)) =  "San Marino"
	set countriesEng($I(count)) =  "Saudi Arabia"
	set countriesEng($I(count)) =  "Scotland"
	set countriesEng($I(count)) =  "Senegal"
	set countriesEng($I(count)) =  "Serbia"
	set countriesEng($I(count)) =  "Seychelles"
	set countriesEng($I(count)) =  "Sierra Leone"
	set countriesEng($I(count)) =  "Singapore"
	set countriesEng($I(count)) =  "Slovakia"
	set countriesEng($I(count)) =  "Slovenia"
	set countriesEng($I(count)) =  "So Tomé and Príncipe"
	set countriesEng($I(count)) =  "Solomon Islands"
	set countriesEng($I(count)) =  "Somalia"
	set countriesEng($I(count)) =  "South Africa"
	set countriesEng($I(count)) =  "South Georgia and the South Sandwich Islands"
	set countriesEng($I(count)) =  "Spain"
	set countriesEng($I(count)) =  "Sri Lanka"
	set countriesEng($I(count)) =  "Sudan"
	set countriesEng($I(count)) =  "Suriname"
	set countriesEng($I(count)) =  "Svalbard and Jan Mayen"
	set countriesEng($I(count)) =  "Swaziland"
	set countriesEng($I(count)) =  "Sweden"
	set countriesEng($I(count)) =  "Switzerland"
	set countriesEng($I(count)) =  "Syrian Arab Republic"
	set countriesEng($I(count)) =  "Tajikistan"
	set countriesEng($I(count)) =  "Tanzania, United Republic Of"
	set countriesEng($I(count)) =  "Thailand"
	set countriesEng($I(count)) =  "Timor-Leste"
	set countriesEng($I(count)) =  "Togo"
	set countriesEng($I(count)) =  "Tokelau"
	set countriesEng($I(count)) =  "Tonga"
	set countriesEng($I(count)) =  "Trinidad and Tobago"
	set countriesEng($I(count)) =  "Tunisia"
	set countriesEng($I(count)) =  "Turkey"
	set countriesEng($I(count)) =  "Turkmenistan"
	set countriesEng($I(count)) =  "Turks and Caicos Islands"
	set countriesEng($I(count)) =  "Tuvalu"
	set countriesEng($I(count)) =  "Uganda"
	set countriesEng($I(count)) =  "Ukraine"
	set countriesEng($I(count)) =  "United Arab Emirates"
	set countriesEng($I(count)) =  "United Kingdom"
	set countriesEng($I(count)) =  "United States"
	set countriesEng($I(count)) =  "Uruguay"
	set countriesEng($I(count)) =  "Uzbekistan"
	set countriesEng($I(count)) =  "Vanuatu"
	set countriesEng($I(count)) =  "Vatican City State"
	set countriesEng($I(count)) =  "Venezuela"
	set countriesEng($I(count)) =  "Vietnam"
	set countriesEng($I(count)) =  "Virgin Islands, British"
	set countriesEng($I(count)) =  "Virgin Islands, U.S."
	set countriesEng($I(count)) =  "Wales"
	set countriesEng($I(count)) =  "Wallis and Futuna"
	set countriesEng($I(count)) =  "Western Sahara"
	set countriesEng($I(count)) =  "Yemen"
	set countriesEng($I(count)) =  "Yugoslavia"
	set countriesEng($I(count)) =  "Zambia"
	set countriesEng($I(count)) =  "Zimbabwe"
	set countriesEng($I(count)) =  "--Unknown--"
	
	
	
	
	set count = 0
	set countriesRus($I(count)) =  "Афганистан"
	set countriesRus($I(count)) =  "Албания"
	set countriesRus($I(count)) =  "Алжир"
	set countriesRus($I(count)) =  "Американское Самоа"
	set countriesRus($I(count)) =  "Андорра"
	set countriesRus($I(count)) =  "Ангола"
	set countriesRus($I(count)) =  "Ангилья"
	set countriesRus($I(count)) =  "Антарктида"
	set countriesRus($I(count)) =  "Антигуа и Барбуда"
	set countriesRus($I(count)) =  "Аргентина"
	set countriesRus($I(count)) =  "Армения"
	set countriesRus($I(count)) =  "Аруба"
	set countriesRus($I(count)) =  "Австралия"
	set countriesRus($I(count)) =  "Австрия"
	set countriesRus($I(count)) =  "Азербайджан"
	set countriesRus($I(count)) =  "Багамские острова"
	set countriesRus($I(count)) =  "Бахрейн"
	set countriesRus($I(count)) =  "Бангладеш"
	set countriesRus($I(count)) =  "Барбадос"
	set countriesRus($I(count)) =  "Беларусь"
	set countriesRus($I(count)) =  "Бельгия"
	set countriesRus($I(count)) =  "Белиз"
	set countriesRus($I(count)) =  "Бенин"
	set countriesRus($I(count)) =  "Бермудские острова"
	set countriesRus($I(count)) =  "Бутан"
	set countriesRus($I(count)) =  "Боливия"
	set countriesRus($I(count)) =  "Босния и Герцеговина"
	set countriesRus($I(count)) =  "Ботсвана"
	set countriesRus($I(count)) =  "Остров Буве"
	set countriesRus($I(count)) =  "Бразилия"
	set countriesRus($I(count)) =  "Бруней-Даруссалам"
	set countriesRus($I(count)) =  "Болгария"
	set countriesRus($I(count)) =  "Буркина-Фасо"
	set countriesRus($I(count)) =  "Бурунди"
	set countriesRus($I(count)) =  "Камбоджа"
	set countriesRus($I(count)) =  "Камерун"
	set countriesRus($I(count)) =  "Канада"
	set countriesRus($I(count)) =  "Кабо-Верде"
	set countriesRus($I(count)) =  "Каймановы острова"
	set countriesRus($I(count)) =  "Центрально-Африканская Республика"
	set countriesRus($I(count)) =  "Чад"
	set countriesRus($I(count)) =  "Чили"
	set countriesRus($I(count)) =  "Китайская Народная Республика"
	set countriesRus($I(count)) =  "китайский Тайбэй"
	set countriesRus($I(count)) =  "Остров Рождества"
	set countriesRus($I(count)) =  "Кокосовые ( Килинг) острова"
	set countriesRus($I(count)) =  "Колумбия"
	set countriesRus($I(count)) =  "Коморские острова"
	set countriesRus($I(count)) =  "Республика Конго"
	set countriesRus($I(count)) =  "острова Кука"
	set countriesRus($I(count)) =  "Коста-Рика"
	set countriesRus($I(count)) =  "Берег Слоновой Кости"
	set countriesRus($I(count)) =  "Хорватия"
	set countriesRus($I(count)) =  "Куба"
	set countriesRus($I(count)) =  "Кипр"
	set countriesRus($I(count)) =  "Чешская республика"
	set countriesRus($I(count)) =  "Дания"
	set countriesRus($I(count)) =  "Джибути"
	set countriesRus($I(count)) =  "Доминика"
	set countriesRus($I(count)) =  "Доминиканская Республика"
	set countriesRus($I(count)) =  "Эквадор"
	set countriesRus($I(count)) =  "ЕГИПЕТ"
	set countriesRus($I(count)) =  "Сальвадор"
	set countriesRus($I(count)) =  "Англия"
	set countriesRus($I(count)) =  "Экваториальная Гвинея"
	set countriesRus($I(count)) =  "Эстония"
	set countriesRus($I(count)) =  "Эфиопия"
	set countriesRus($I(count)) =  "Фолклендские острова"
	set countriesRus($I(count)) =  "Фарерские острова"
	set countriesRus($I(count)) =  "Фиджи"
	set countriesRus($I(count)) =  "Финляндия"
	set countriesRus($I(count)) =  "Франция"
	set countriesRus($I(count)) =  "Французская Гвиана"
	set countriesRus($I(count)) =  "Французская Полинезия"
	set countriesRus($I(count)) =  "Габон"
	set countriesRus($I(count)) =  "Гамбия"
	set countriesRus($I(count)) =  "Грузия"
	set countriesRus($I(count)) =  "Германия"
	set countriesRus($I(count)) =  "Гана"
	set countriesRus($I(count)) =  "Гибралтар"
	set countriesRus($I(count)) =  "Греция"
	set countriesRus($I(count)) =  "Гренландия"
	set countriesRus($I(count)) =  "Гренада"
	set countriesRus($I(count)) =  "Гваделупа"
	set countriesRus($I(count)) =  "Гуам"
	set countriesRus($I(count)) =  "Гватемала"
	set countriesRus($I(count)) =  "Гвинея"
	set countriesRus($I(count)) =  "Гвинея-Бисау"
	set countriesRus($I(count)) =  "Гайана"
	set countriesRus($I(count)) =  "Гаити"
	set countriesRus($I(count)) =  "Остров Херд и Макдональд"
	set countriesRus($I(count)) =  "Гондурас"
	set countriesRus($I(count)) =  "Гонконг"
	set countriesRus($I(count)) =  "Венгрия"
	set countriesRus($I(count)) =  "Исландия"
	set countriesRus($I(count)) =  "Индия"
	set countriesRus($I(count)) =  "Индонезия"
	set countriesRus($I(count)) =  "Иран, Исламская Республика"
	set countriesRus($I(count)) =  "Ирак"
	set countriesRus($I(count)) =  "Ирландия , Республика"
	set countriesRus($I(count)) =  "Израиль"
	set countriesRus($I(count)) =  "Италия"
	set countriesRus($I(count)) =  "Ямайка"
	set countriesRus($I(count)) =  "Япония"
	set countriesRus($I(count)) =  "Иордания"
	set countriesRus($I(count)) =  "Казахстан"
	set countriesRus($I(count)) =  "Кения"
	set countriesRus($I(count)) =  "Кирибати"
	set countriesRus($I(count)) =  "Корея"
	set countriesRus($I(count)) =  "Корея , Корейская Народно-Демократическая Республика"
	set countriesRus($I(count)) =  "Кувейт"
	set countriesRus($I(count)) =  "Киргизия"
	set countriesRus($I(count)) =  "Лаосская Народно-Демократическая Республика"
	set countriesRus($I(count)) =  "Латвия"
	set countriesRus($I(count)) =  "Ливан"
	set countriesRus($I(count)) =  "Лесото"
	set countriesRus($I(count)) =  "Либерия"
	set countriesRus($I(count)) =  "Ливийская Арабская Джамахирия"
	set countriesRus($I(count)) =  "Лихтенштейн"
	set countriesRus($I(count)) =  "Литва"
	set countriesRus($I(count)) =  "Люксембург"
	set countriesRus($I(count)) =  "Макао"
	set countriesRus($I(count)) =  "Македония"
	set countriesRus($I(count)) =  "Мадагаскар"
	set countriesRus($I(count)) =  "Малави"
	set countriesRus($I(count)) =  "Малайзия"
	set countriesRus($I(count)) =  "Мальдивы"
	set countriesRus($I(count)) =  "Мали"
	set countriesRus($I(count)) =  "Мальта"
	set countriesRus($I(count)) =  "Маршалловы острова"
	set countriesRus($I(count)) =  "Мартиника"
	set countriesRus($I(count)) =  "Мавритания"
	set countriesRus($I(count)) =  "Маврикий"
	set countriesRus($I(count)) =  "Майотта"
	set countriesRus($I(count)) =  "Мексика"
	set countriesRus($I(count)) =  "Микронезия, Федеративные Штаты"
	set countriesRus($I(count)) =  "Молдова"
	set countriesRus($I(count)) =  "Монако"
	set countriesRus($I(count)) =  "Монголия"
	set countriesRus($I(count)) =  "Черногория"
	set countriesRus($I(count)) =  "Монтсеррат"
	set countriesRus($I(count)) =  "Марокко"
	set countriesRus($I(count)) =  "Мозамбик"
	set countriesRus($I(count)) =  "Мьянма"
	set countriesRus($I(count)) =  "Намибия"
	set countriesRus($I(count)) =  "Науру"
	set countriesRus($I(count)) =  "Непал"
	set countriesRus($I(count)) =  "Нидерланды"
	set countriesRus($I(count)) =  "Нидерландские Антильские острова"
	set countriesRus($I(count)) =  "Новая Каледония"
	set countriesRus($I(count)) =  "Новая Зеландия"
	set countriesRus($I(count)) =  "Никарагуа"
	set countriesRus($I(count)) =  "Нигер"
	set countriesRus($I(count)) =  "Нигерия"
	set countriesRus($I(count)) =  "Ниуэ"
	set countriesRus($I(count)) =  "Остров Норфолк"
	set countriesRus($I(count)) =  "Северная Ирландия"
	set countriesRus($I(count)) =  "Северные Марианские острова"
	set countriesRus($I(count)) =  "Норвегия"
	set countriesRus($I(count)) =  "Оман"
	set countriesRus($I(count)) =  "Пакистан"
	set countriesRus($I(count)) =  "Палау"
	set countriesRus($I(count)) =  "Панама"
	set countriesRus($I(count)) =  "Папуа-Новая Гвинея"
	set countriesRus($I(count)) =  "Парагвай"
	set countriesRus($I(count)) =  "Перу"
	set countriesRus($I(count)) =  "Филиппины"
	set countriesRus($I(count)) =  "Питкэрн"
	set countriesRus($I(count)) =  "Польша"
	set countriesRus($I(count)) =  "Португалия"
	set countriesRus($I(count)) =  "Пуэрто-Рико"
	set countriesRus($I(count)) =  "Катар"
	set countriesRus($I(count)) =  "Республика Косово"
	set countriesRus($I(count)) =  "Реюньон"
	set countriesRus($I(count)) =  "Румыния"
	set countriesRus($I(count)) =  "Российская Федерация"
	set countriesRus($I(count)) =  "Руанда"
	set countriesRus($I(count)) =  "Остров Святой Елены"
	set countriesRus($I(count)) =  "Сент-Китс и Невис"
	set countriesRus($I(count)) =  "Сент-Люсия"
	set countriesRus($I(count)) =  "Сен-Пьер и Микелон"
	set countriesRus($I(count)) =  "Сент-Винсент и Гренадины"
	set countriesRus($I(count)) =  "Самоа"
	set countriesRus($I(count)) =  "Сан - Марино"
	set countriesRus($I(count)) =  "Саудовская Аравия"
	set countriesRus($I(count)) =  "Шотландия"
	set countriesRus($I(count)) =  "Сенегал"
	set countriesRus($I(count)) =  "Сербия"
	set countriesRus($I(count)) =  "Сейшельские острова"
	set countriesRus($I(count)) =  "Сьерра-Леоне"
	set countriesRus($I(count)) =  "Сингапур"
	set countriesRus($I(count)) =  "Словакия"
	set countriesRus($I(count)) =  "Словения"
	set countriesRus($I(count)) =  "Так -Томе и Принсипи"
	set countriesRus($I(count)) =  "Соломоновы Острова"
	set countriesRus($I(count)) =  "Сомали"
	set countriesRus($I(count)) =  "ЮАР"
	set countriesRus($I(count)) =  "Южная Георгия иЮжные Сандвичевы острова"
	set countriesRus($I(count)) =  "Испания"
	set countriesRus($I(count)) =  "Шри Ланка"
	set countriesRus($I(count)) =  "Судан"
	set countriesRus($I(count)) =  "Суринам"
	set countriesRus($I(count)) =  "Шпицберген и Ян-Майен"
	set countriesRus($I(count)) =  "Свазиленд"
	set countriesRus($I(count)) =  "Швеция"
	set countriesRus($I(count)) =  "Швейцария"
	set countriesRus($I(count)) =  "Сирийская Арабская Республика"
	set countriesRus($I(count)) =  "Таджикистан"
	set countriesRus($I(count)) =  "Танзания, Объединенная Республика"
	set countriesRus($I(count)) =  "Таиланд"
	set countriesRus($I(count)) =  "Тимор-Лешти"
	set countriesRus($I(count)) =  "Того"
	set countriesRus($I(count)) =  "Токелау"
	set countriesRus($I(count)) =  "Тонга"
	set countriesRus($I(count)) =  "Тринидад и Тобаго"
	set countriesRus($I(count)) =  "Тунис"
	set countriesRus($I(count)) =  "Турция"
	set countriesRus($I(count)) =  "Туркменистан"
	set countriesRus($I(count)) =  "Острова Теркс и Кайкос"
	set countriesRus($I(count)) =  "Тувалу"
	set countriesRus($I(count)) =  "Уганда"
	set countriesRus($I(count)) =  "Украина"
	set countriesRus($I(count)) =  "Объединенные Арабские Эмираты"
	set countriesRus($I(count)) =  "Великобритания"
	set countriesRus($I(count)) =  "США"
	set countriesRus($I(count)) =  "Уругвай"
	set countriesRus($I(count)) =  "Узбекистан"
	set countriesRus($I(count)) =  "Вануату"
	set countriesRus($I(count)) =  "Государство-город Ватикан"
	set countriesRus($I(count)) =  "Венесуэла"
	set countriesRus($I(count)) =  "Вьетнам"
	set countriesRus($I(count)) =  "Виргинские острова, Британские"
	set countriesRus($I(count)) =  "Виргинские острова, США"
	set countriesRus($I(count)) =  "Уэльс"
	set countriesRus($I(count)) =  "Уоллис и Футуна"
	set countriesRus($I(count)) =  "Западная Сахара"
	set countriesRus($I(count)) =  "Йемен"
	set countriesRus($I(count)) =  "Югославия"
	set countriesRus($I(count)) =  "Замбия"
	set countriesRus($I(count)) =  "Зимбабве"
	set countriesRus($I(count)) =  "--Неизвестна--"
	
	for i=1:1:count{ 
		set nameEng = countriesEng(i)
		set nameRus = countriesRus(i)
		
		set country = ##class(Dance.Data.Country).%New()
		do ##class(%MessageDictionary).SetSessionLanguage("en")
		set country.Name = ##class(Dance.Data.Localization.LText).Create(nameEng)
		do ##class(%MessageDictionary).SetSessionLanguage("ru")
		set country.Name.Value = nameRus
		set country.WDSFName = nameEng
		do country.%Save()	
	}
	
	quit $$$OK
]]></Implementation>
</Method>
</Class>
</Export>
